sso_utils/sso_utils.py
spk_dev_utils-1.0.0.dist-info/METADATA
spk_dev_utils-1.0.0.dist-info/WHEEL
spk_dev_utils-1.0.0.dist-info/top_level.txt
spk_dev_utils-1.0.0.dist-info/RECORD
