Metadata-Version: 2.1
Name: spk-dev-utils
Version: 1.0.0
Summary: Utilities for working with SSO
Author-email: dahannajr <david.hanna@kickstepinc.com>
Requires-Python: >=3
Requires-Dist: boto3
